MANIFEST.in
README.md
setup.py
edgarsearch/__init__.py
edgarsearch/edgarsearch.py
edgarsearch/filingsbatch.py
edgarsearch/indexhandler.py
edgarsearch/mpworker.py
edgarsearch/tools.py
edgarsearch.egg-info/PKG-INFO
edgarsearch.egg-info/SOURCES.txt
edgarsearch.egg-info/dependency_links.txt
edgarsearch.egg-info/requires.txt
edgarsearch.egg-info/top_level.txt