Metadata-Version: 1.1
Name: edgarsearch
Version: 0.3
Summary: Crawl EDGAR database to download index files and filings.
Home-page: https://github.com/markdembo/edgarsearch
Author: Mark Dembo
Author-email: mark.dembo@student.unisg.ch
License: MIT
Download-URL: https://github.com/markdembo/edgarsearch/archive/0.3.tar.gz
Keywords: EDGAR index filings 8-K 10-K
Platform: UNKNOWN
